MANIFEST.in
README.txt
setup.py
plugins/coily
springpython/COPYRIGHT
springpython/LICENSE.txt
springpython/__init__.py
springpython/util.py
springpython.egg-info/PKG-INFO
springpython.egg-info/SOURCES.txt
springpython.egg-info/dependency_links.txt
springpython.egg-info/top_level.txt
springpython/aop/__init__.py
springpython/aop/utils.py
springpython/config/__init__.py
springpython/config/_config_base.py
springpython/config/_python_config.py
springpython/config/_xml_config.py
springpython/config/_yaml_config.py
springpython/config/decorator.py
springpython/container/__init__.py
springpython/context/__init__.py
springpython/context/scope.py
springpython/database/__init__.py
springpython/database/core.py
springpython/database/factory.py
springpython/database/transaction.py
springpython/factory/__init__.py
springpython/images/coily.jpg
springpython/images/spring_python_white.png
springpython/jms/__init__.py
springpython/jms/core.py
springpython/jms/factory.py
springpython/jms/listener.py
springpython/remoting/__init__.py
springpython/remoting/http.py
springpython/remoting/xmlrpc.py
springpython/remoting/hessian/__init__.py
springpython/remoting/hessian/hessianlib.py
springpython/remoting/pyro/Pyro4DaemonHolder.py
springpython/remoting/pyro/PyroDaemonHolder.py
springpython/remoting/pyro/__init__.py
springpython/security/__init__.py
springpython/security/cherrypy3.py
springpython/security/intercept.py
springpython/security/vote.py
springpython/security/web.py
springpython/security/context/SecurityContextHolder.py
springpython/security/context/__init__.py
springpython/security/providers/Ldap.py
springpython/security/providers/_Ldap_cpython.py
springpython/security/providers/_Ldap_jython.py
springpython/security/providers/__init__.py
springpython/security/providers/dao.py
springpython/security/providers/encoding.py
springpython/security/userdetails/__init__.py
springpython/security/userdetails/dao.py