Metadata-Version: 1.0
Name: springpython
Version: 1.3.0.RC1
Summary: Spring Python
Home-page: http://springpython.webfactional.com
Author: Greg L. Turnquist
Author-email: greg.turnquist at springsource dot com
License: Apache Software License (http://www.apache.org/licenses/LICENSE-2.0)
Platform: Python >= 2.6
Classifier: License :: OSI Approved :: Apache Software License
Classifier: Intended Audience :: Developers
Classifier: Development Status :: 5 - Production/Stable
Classifier: Topic :: Software Development :: Libraries :: Python Modules
Classifier: Programming Language :: Python
Classifier: Operating System :: OS Independent
